{
  "model": "transformer",
  "n_sites": 197,
  "seq_len": 24,
  "pred_len": 6,
  "d_model": 128,
  "n_layers": 2,
  "n_params": 3922590,
  "test_mse": 2.620781660079956,
  "test_mae": 0.6520955562591553,
  "history": [
    {
      "epoch": 1,
      "train_mse": 0.8542024682438563,
      "val_mse": 1.6699014902114868,
      "val_mae": 0.47747471928596497,
      "lr": 0.001
    },
    {
      "epoch": 2,
      "train_mse": 0.6083797029559574,
      "val_mse": 1.4453673362731934,
      "val_mae": 0.4760890603065491,
      "lr": 0.001
    },
    {
      "epoch": 3,
      "train_mse": 0.5334209102013755,
      "val_mse": 1.3043292760849,
      "val_mae": 0.47026994824409485,
      "lr": 0.001
    },
    {
      "epoch": 4,
      "train_mse": 0.48014868038987357,
      "val_mse": 1.5043983459472656,
      "val_mae": 0.47679728269577026,
      "lr": 0.001
    },
    {
      "epoch": 5,
      "train_mse": 0.44172106588643695,
      "val_mse": 1.407312035560608,
      "val_mae": 0.47070586681365967,
      "lr": 0.001
    },
    {
      "epoch": 6,
      "train_mse": 0.41579789396316286,
      "val_mse": 1.5764820575714111,
      "val_mae": 0.46528375148773193,
      "lr": 0.001
    },
    {
      "epoch": 7,
      "train_mse": 0.39421907705920084,
      "val_mse": 1.566794991493225,
      "val_mae": 0.46636372804641724,
      "lr": 0.0005
    },
    {
      "epoch": 8,
      "train_mse": 0.3568376059096957,
      "val_mse": 1.5418322086334229,
      "val_mae": 0.4664628207683563,
      "lr": 0.0005
    },
    {
      "epoch": 9,
      "train_mse": 0.34427362585824633,
      "val_mse": 1.5926246643066406,
      "val_mae": 0.46344253420829773,
      "lr": 0.0005
    },
    {
      "epoch": 10,
      "train_mse": 0.3369461437539449,
      "val_mse": 1.548317313194275,
      "val_mae": 0.4709463119506836,
      "lr": 0.0005
    },
    {
      "epoch": 11,
      "train_mse": 0.3294722478068064,
      "val_mse": 1.55986750125885,
      "val_mae": 0.4811377227306366,
      "lr": 0.00025
    }
  ]
}